{
  "db_name": "PostgreSQL",
  "query": "\n        INSERT INTO relay_invocations\n            (id, grant_id, granter_agent_id, grantee_agent_id, capability_id,\n             capability_name, invoked_by_user_id, status, elapsed_ms,\n             error_message, input_preview)\n        VALUES ($1, $2, $3, $4, $5, $6, $7, $8, $9, $10, $11)\n        ",
  "describe": {
    "columns": [],
    "parameters": {
      "Left": [
        "Uuid",
        "Uuid",
        "Uuid",
        "Uuid",
        "Uuid",
        "Text",
        "Uuid",
        "Text",
        "Int4",
        "Text",
        "Jsonb"
      ]
    },
    "nullable": []
  },
  "hash": "f0897a69a1c89866ff7b9569c33cb9fd9b1bc04a4a04c5bee2d923dea93a8119"
}
